README.md
setup.cfg
setup.py
funniestst/__init__.py
funniestst.egg-info/PKG-INFO
funniestst.egg-info/SOURCES.txt
funniestst.egg-info/dependency_links.txt
funniestst.egg-info/not-zip-safe
funniestst.egg-info/top_level.txt