Metadata-Version: 1.1
Name: funniestst
Version: 0.2
Summary: Jenos greater then Khan
Home-page: http://github.com/shubhstiws
Author: Shubhankar Tiwari
Author-email: flyingcircus@example.com
License: MIT
Keywords: paladins setuptools development
Platform: UNKNOWN
Classifier: Development Status :: 3 - Alpha
Classifier: Intended Audience :: Developers
Classifier: Topic :: Software Development :: Build Tools
Classifier: License :: OSI Approved :: MIT License
Classifier: Programming Language :: Python :: 3.6
